{
"meta":{"test_sets":[],"test_metrics":[],"learn_metrics":[{"best_value":"Min","name":"RMSE"}],"launch_mode":"Train","parameters":"","iteration_count":200,"learn_sets":["learn"],"name":"experiment"},
"iterations":[
{"learn":[0.09928388661],"iteration":0,"passed_time":0.03080494839,"remaining_time":6.130184729},
{"learn":[0.09880108753],"iteration":1,"passed_time":0.03513458832,"remaining_time":3.478324244},
{"learn":[0.09834032023],"iteration":2,"passed_time":0.0390491089,"remaining_time":2.564224818},
{"learn":[0.09788095016],"iteration":3,"passed_time":0.0431159547,"remaining_time":2.11268178},
{"learn":[0.09751717001],"iteration":4,"passed_time":0.04705432571,"remaining_time":1.835118703},
{"learn":[0.09712154331],"iteration":5,"passed_time":0.05101723191,"remaining_time":1.649557165},
{"learn":[0.09679679579],"iteration":6,"passed_time":0.05498546307,"remaining_time":1.516027767},
{"learn":[0.09652542945],"iteration":7,"passed_time":0.05899342249,"remaining_time":1.41584214},
{"learn":[0.09616309832],"iteration":8,"passed_time":0.06295208139,"remaining_time":1.335983061},
{"learn":[0.095872417],"iteration":9,"passed_time":0.06691923569,"remaining_time":1.271465478},
{"learn":[0.09552741938],"iteration":10,"passed_time":0.07092658652,"remaining_time":1.218647714},
{"learn":[0.09532522951],"iteration":11,"passed_time":0.07486287839,"remaining_time":1.172851761},
{"learn":[0.09507921533],"iteration":12,"passed_time":0.0787460851,"remaining_time":1.132732147},
{"learn":[0.09483778959],"iteration":13,"passed_time":0.08275423456,"remaining_time":1.099449116},
{"learn":[0.0946171665],"iteration":14,"passed_time":0.08663327176,"remaining_time":1.068477018},
{"learn":[0.09435498312],"iteration":15,"passed_time":0.09064214767,"remaining_time":1.042384698},
{"learn":[0.09411458831],"iteration":16,"passed_time":0.09467474972,"remaining_time":1.019145835},
{"learn":[0.0939418601],"iteration":17,"passed_time":0.09855931635,"remaining_time":0.9965441986},
{"learn":[0.09373479821],"iteration":18,"passed_time":0.1024875362,"remaining_time":0.9763286342},
{"learn":[0.09359017669],"iteration":19,"passed_time":0.106545011,"remaining_time":0.9589050991},
{"learn":[0.09341780534],"iteration":20,"passed_time":0.1104545306,"remaining_time":0.9414933797},
{"learn":[0.09325978341],"iteration":21,"passed_time":0.1152989116,"remaining_time":0.9328730121},
{"learn":[0.09306939478],"iteration":22,"passed_time":0.1194836497,"remaining_time":0.9195046082},
{"learn":[0.09295751091],"iteration":23,"passed_time":0.123344802,"remaining_time":0.9045285483},
{"learn":[0.09282995629],"iteration":24,"passed_time":0.1272941124,"remaining_time":0.8910587869},
{"learn":[0.09272509744],"iteration":25,"passed_time":0.1312596326,"remaining_time":0.8784298488},
{"learn":[0.09257102085],"iteration":26,"passed_time":0.1351004361,"remaining_time":0.8656435352},
{"learn":[0.09249083707],"iteration":27,"passed_time":0.1389275164,"remaining_time":0.8534118862},
{"learn":[0.09238720581],"iteration":28,"passed_time":0.1428173037,"remaining_time":0.8421296184},
{"learn":[0.0922517797],"iteration":29,"passed_time":0.1466196908,"remaining_time":0.8308449144},
{"learn":[0.09212165654],"iteration":30,"passed_time":0.1504740701,"remaining_time":0.8203263822},
{"learn":[0.09200791001],"iteration":31,"passed_time":0.1543198803,"remaining_time":0.8101793715},
{"learn":[0.09188141387],"iteration":32,"passed_time":0.158117559,"remaining_time":0.8001706774},
{"learn":[0.09175092413],"iteration":33,"passed_time":0.1619317017,"remaining_time":0.7906077202},
{"learn":[0.09163270116],"iteration":34,"passed_time":0.165867741,"remaining_time":0.7819479219},
{"learn":[0.09153649119],"iteration":35,"passed_time":0.1695853073,"remaining_time":0.7725552889},
{"learn":[0.09141723538],"iteration":36,"passed_time":0.1734774617,"remaining_time":0.7642385473},
{"learn":[0.09133735834],"iteration":37,"passed_time":0.1774350557,"remaining_time":0.7564336587},
{"learn":[0.09118642844],"iteration":38,"passed_time":0.1812046167,"remaining_time":0.7480498279},
{"learn":[0.09105030586],"iteration":39,"passed_time":0.1850745251,"remaining_time":0.7402981003},
{"learn":[0.09097776578],"iteration":40,"passed_time":0.1889678549,"remaining_time":0.7328265592},
{"learn":[0.09088971745],"iteration":41,"passed_time":0.1928709077,"remaining_time":0.7255619861},
{"learn":[0.09078689144],"iteration":42,"passed_time":0.1967380578,"remaining_time":0.7183226761},
{"learn":[0.09075492934],"iteration":43,"passed_time":0.2005303851,"remaining_time":0.7109713654},
{"learn":[0.09066112654],"iteration":44,"passed_time":0.2042889682,"remaining_time":0.7036620016},
{"learn":[0.09055783908],"iteration":45,"passed_time":0.2080340854,"remaining_time":0.6964619381},
{"learn":[0.09050145622],"iteration":46,"passed_time":0.2117188937,"remaining_time":0.689212569},
{"learn":[0.09040034961],"iteration":47,"passed_time":0.2155172252,"remaining_time":0.682471213},
{"learn":[0.09034861655],"iteration":48,"passed_time":0.2195068684,"remaining_time":0.6764395332},
{"learn":[0.09021141742],"iteration":49,"passed_time":0.2234216151,"remaining_time":0.6702648453},
{"learn":[0.09012914946],"iteration":50,"passed_time":0.2272590317,"remaining_time":0.6639528573},
{"learn":[0.08998163766],"iteration":51,"passed_time":0.2311056549,"remaining_time":0.6577622487},
{"learn":[0.08991118766],"iteration":52,"passed_time":0.2349299897,"remaining_time":0.6515982733},
{"learn":[0.08981039294],"iteration":53,"passed_time":0.2386203299,"remaining_time":0.6451586697},
{"learn":[0.089765279],"iteration":54,"passed_time":0.2424958631,"remaining_time":0.6393072754},
{"learn":[0.08965598246],"iteration":55,"passed_time":0.2463986986,"remaining_time":0.6335966535},
{"learn":[0.08959820075],"iteration":56,"passed_time":0.2501757583,"remaining_time":0.6276339199},
{"learn":[0.08950138125],"iteration":57,"passed_time":0.2539516064,"remaining_time":0.6217435881},
{"learn":[0.0894525537],"iteration":58,"passed_time":0.2577605364,"remaining_time":0.6160039938},
{"learn":[0.08938144426],"iteration":59,"passed_time":0.2614229384,"remaining_time":0.6099868563},
{"learn":[0.08927424913],"iteration":60,"passed_time":0.2652463126,"remaining_time":0.6044137287},
{"learn":[0.08922086132],"iteration":61,"passed_time":0.2689024595,"remaining_time":0.5985248293},
{"learn":[0.08912147028],"iteration":62,"passed_time":0.2725753511,"remaining_time":0.5927432238},
{"learn":[0.0890615703],"iteration":63,"passed_time":0.2763398437,"remaining_time":0.5872221678},
{"learn":[0.08900990737],"iteration":64,"passed_time":0.280171156,"remaining_time":0.5818939393},
{"learn":[0.08894167214],"iteration":65,"passed_time":0.2838105294,"remaining_time":0.576221378},
{"learn":[0.08887712166],"iteration":66,"passed_time":0.2876371727,"remaining_time":0.5709812532},
{"learn":[0.08879907375],"iteration":67,"passed_time":0.2913276435,"remaining_time":0.5655183669},
{"learn":[0.08874986745],"iteration":68,"passed_time":0.2949449322,"remaining_time":0.5599679148},
{"learn":[0.08871106135],"iteration":69,"passed_time":0.2987270819,"remaining_time":0.5547788664},
{"learn":[0.08866044674],"iteration":70,"passed_time":0.3024379144,"remaining_time":0.5494998727},
{"learn":[0.08859222515],"iteration":71,"passed_time":0.3060796204,"remaining_time":0.5441415474},
{"learn":[0.08851623252],"iteration":72,"passed_time":0.3098898149,"remaining_time":0.5391233767},
{"learn":[0.08845909952],"iteration":73,"passed_time":0.3136153699,"remaining_time":0.5339937379},
{"learn":[0.08840627262],"iteration":74,"passed_time":0.3174752658,"remaining_time":0.529125443},
{"learn":[0.08834056059],"iteration":75,"passed_time":0.3213042375,"remaining_time":0.5242332297},
{"learn":[0.08829263263],"iteration":76,"passed_time":0.3251143655,"remaining_time":0.5193385319},
{"learn":[0.08824075356],"iteration":77,"passed_time":0.3287801608,"remaining_time":0.5142458926},
{"learn":[0.0882058422],"iteration":78,"passed_time":0.3325390158,"remaining_time":0.5093319102},
{"learn":[0.08812779912],"iteration":79,"passed_time":0.3363328642,"remaining_time":0.5044992963},
{"learn":[0.08809109041],"iteration":80,"passed_time":0.3400687419,"remaining_time":0.499607164},
{"learn":[0.08801023735],"iteration":81,"passed_time":0.3438852155,"remaining_time":0.4948592125},
{"learn":[0.08796059361],"iteration":82,"passed_time":0.3475881821,"remaining_time":0.4899737025},
{"learn":[0.08792732306],"iteration":83,"passed_time":0.3511900299,"remaining_time":0.484976708},
{"learn":[0.08790241388],"iteration":84,"passed_time":0.354994521,"remaining_time":0.4802867049},
{"learn":[0.08787536317],"iteration":85,"passed_time":0.3587698792,"remaining_time":0.4755786771},
{"learn":[0.08782400478],"iteration":86,"passed_time":0.3624265882,"remaining_time":0.4707379824},
{"learn":[0.08775727419],"iteration":87,"passed_time":0.3661469016,"remaining_time":0.4660051475},
{"learn":[0.08772022516],"iteration":88,"passed_time":0.3697772561,"remaining_time":0.4611828699},
{"learn":[0.08763146536],"iteration":89,"passed_time":0.3736070304,"remaining_time":0.456630815},
{"learn":[0.0875770529],"iteration":90,"passed_time":0.3772941457,"remaining_time":0.4519237569},
{"learn":[0.08754570179],"iteration":91,"passed_time":0.3811015875,"remaining_time":0.4473801244},
{"learn":[0.08751505129],"iteration":92,"passed_time":0.3847754669,"remaining_time":0.4426986555},
{"learn":[0.0874945059],"iteration":93,"passed_time":0.3884866955,"remaining_time":0.4380807418},
{"learn":[0.08740683001],"iteration":94,"passed_time":0.392258585,"remaining_time":0.4335489624},
{"learn":[0.08735718831],"iteration":95,"passed_time":0.3959660972,"remaining_time":0.4289632719},
{"learn":[0.08731060128],"iteration":96,"passed_time":0.3997550328,"remaining_time":0.4244821482},
{"learn":[0.08727475922],"iteration":97,"passed_time":0.4034335042,"remaining_time":0.4199001779},
{"learn":[0.08722788364],"iteration":98,"passed_time":0.4072318196,"remaining_time":0.4154587251},
{"learn":[0.08716888083],"iteration":99,"passed_time":0.4110641992,"remaining_time":0.4110641992},
{"learn":[0.08714209585],"iteration":100,"passed_time":0.4148547753,"remaining_time":0.4066398292},
{"learn":[0.08705343888],"iteration":101,"passed_time":0.4184942193,"remaining_time":0.4020826813},
{"learn":[0.08702492601],"iteration":102,"passed_time":0.4221984656,"remaining_time":0.3976043802},
{"learn":[0.08694768427],"iteration":103,"passed_time":0.4259459081,"remaining_time":0.3931808383},
{"learn":[0.08692456264],"iteration":104,"passed_time":0.4343315483,"remaining_time":0.3929666389},
{"learn":[0.08688935625],"iteration":105,"passed_time":0.4381483082,"remaining_time":0.3885466129},
{"learn":[0.08685472421],"iteration":106,"passed_time":0.4419963242,"remaining_time":0.3841650294},
{"learn":[0.08680546493],"iteration":107,"passed_time":0.4456518994,"remaining_time":0.3796293958},
{"learn":[0.08674670562],"iteration":108,"passed_time":0.4494437649,"remaining_time":0.3752236936},
{"learn":[0.0866977013],"iteration":109,"passed_time":0.4532157249,"remaining_time":0.3708128658},
{"learn":[0.08660969572],"iteration":110,"passed_time":0.456857556,"remaining_time":0.3663092116},
{"learn":[0.0865616034],"iteration":111,"passed_time":0.4606945757,"remaining_time":0.3619743095},
{"learn":[0.08651605159],"iteration":112,"passed_time":0.4644391637,"remaining_time":0.3575770552},
{"learn":[0.08648134836],"iteration":113,"passed_time":0.4680993142,"remaining_time":0.3531275528},
{"learn":[0.08644285164],"iteration":114,"passed_time":0.4718711668,"remaining_time":0.3487743406},
{"learn":[0.08640437696],"iteration":115,"passed_time":0.4755971635,"remaining_time":0.344397946},
{"learn":[0.08631799823],"iteration":116,"passed_time":0.479253903,"remaining_time":0.339983538},
{"learn":[0.08629546117],"iteration":117,"passed_time":0.4829613165,"remaining_time":0.3356171861},
{"learn":[0.08626226665],"iteration":118,"passed_time":0.4866902119,"remaining_time":0.3312765308},
{"learn":[0.08622920071],"iteration":119,"passed_time":0.490378849,"remaining_time":0.3269192327},
{"learn":[0.08619387134],"iteration":120,"passed_time":0.4941943292,"remaining_time":0.3226558017},
{"learn":[0.08616003646],"iteration":121,"passed_time":0.497880159,"remaining_time":0.318316823},
{"learn":[0.08613712397],"iteration":122,"passed_time":0.5015415123,"remaining_time":0.3139731418},
{"learn":[0.08609417514],"iteration":123,"passed_time":0.5053499411,"remaining_time":0.3097306091},
{"learn":[0.0860613554],"iteration":124,"passed_time":0.5091691602,"remaining_time":0.3055014961},
{"learn":[0.08602219842],"iteration":125,"passed_time":0.5128351272,"remaining_time":0.3011888842},
{"learn":[0.08596632628],"iteration":126,"passed_time":0.5166091896,"remaining_time":0.2969485893},
{"learn":[0.08593767729],"iteration":127,"passed_time":0.5203516255,"remaining_time":0.2926977893},
{"learn":[0.08589888962],"iteration":128,"passed_time":0.5241505005,"remaining_time":0.2884859344},
{"learn":[0.08586552996],"iteration":129,"passed_time":0.5280029667,"remaining_time":0.2843092898},
{"learn":[0.08581769526],"iteration":130,"passed_time":0.5317743182,"remaining_time":0.2800948699},
{"learn":[0.08578840859],"iteration":131,"passed_time":0.5354609434,"remaining_time":0.2758435163},
{"learn":[0.08576339138],"iteration":132,"passed_time":0.5392285953,"remaining_time":0.2716414728},
{"learn":[0.08574294354],"iteration":133,"passed_time":0.5428467876,"remaining_time":0.2673722984},
{"learn":[0.08569528536],"iteration":134,"passed_time":0.5465242961,"remaining_time":0.2631413277},
{"learn":[0.08567761912],"iteration":135,"passed_time":0.5501603435,"remaining_time":0.2588989852},
{"learn":[0.08564351307],"iteration":136,"passed_time":0.5539591841,"remaining_time":0.2547403547},
{"learn":[0.08562208758],"iteration":137,"passed_time":0.5575808131,"remaining_time":0.2505073218},
{"learn":[0.08559198637],"iteration":138,"passed_time":0.5613403841,"remaining_time":0.2463436218},
{"learn":[0.08556030756],"iteration":139,"passed_time":0.5650275899,"remaining_time":0.2421546814},
{"learn":[0.08551444805],"iteration":140,"passed_time":0.5686823569,"remaining_time":0.2379592841},
{"learn":[0.08548927147],"iteration":141,"passed_time":0.5724708154,"remaining_time":0.2338261077},
{"learn":[0.0854739037],"iteration":142,"passed_time":0.5762608158,"remaining_time":0.2296983671},
{"learn":[0.08542595274],"iteration":143,"passed_time":0.5799178736,"remaining_time":0.2255236175},
{"learn":[0.08539339162],"iteration":144,"passed_time":0.5837093077,"remaining_time":0.2214069788},
{"learn":[0.0853588071],"iteration":145,"passed_time":0.5874866761,"remaining_time":0.2172895925},
{"learn":[0.08532905344],"iteration":146,"passed_time":0.5911691888,"remaining_time":0.2131426327},
{"learn":[0.08529466115],"iteration":147,"passed_time":0.5949442984,"remaining_time":0.2090344832},
{"learn":[0.08525765391],"iteration":148,"passed_time":0.598742536,"remaining_time":0.2049387204},
{"learn":[0.08522858397],"iteration":149,"passed_time":0.6023803195,"remaining_time":0.2007934398},
{"learn":[0.08517330426],"iteration":150,"passed_time":0.6061464125,"remaining_time":0.196696518},
{"learn":[0.085142261],"iteration":151,"passed_time":0.6099220594,"remaining_time":0.1926069661},
{"learn":[0.08510859284],"iteration":152,"passed_time":0.613559227,"remaining_time":0.1884789782},
{"learn":[0.08508923706],"iteration":153,"passed_time":0.6173366964,"remaining_time":0.184399273},
{"learn":[0.08502695041],"iteration":154,"passed_time":0.6211430125,"remaining_time":0.1803318423},
{"learn":[0.08499134039],"iteration":155,"passed_time":0.6247857312,"remaining_time":0.1762216165},
{"learn":[0.0849634306],"iteration":156,"passed_time":0.6285468881,"remaining_time":0.1721497846},
{"learn":[0.08491928214],"iteration":157,"passed_time":0.6322585875,"remaining_time":0.1680687384},
{"learn":[0.08490298175],"iteration":158,"passed_time":0.6360810307,"remaining_time":0.1640208947},
{"learn":[0.0847971924],"iteration":159,"passed_time":0.6398553714,"remaining_time":0.1599638428},
{"learn":[0.08475549002],"iteration":160,"passed_time":0.643562044,"remaining_time":0.1558939113},
{"learn":[0.08471298376],"iteration":161,"passed_time":0.6471799501,"remaining_time":0.1518076426},
{"learn":[0.08467201565],"iteration":162,"passed_time":0.6509348969,"remaining_time":0.1477582281},
{"learn":[0.08465026028],"iteration":163,"passed_time":0.6545505442,"remaining_time":0.1436818268},
{"learn":[0.08462321023],"iteration":164,"passed_time":0.6582856434,"remaining_time":0.1396363486},
{"learn":[0.08460149833],"iteration":165,"passed_time":0.6619784243,"remaining_time":0.1355859423},
{"learn":[0.08457428456],"iteration":166,"passed_time":0.666829932,"remaining_time":0.131768789},
{"learn":[0.08451821638],"iteration":167,"passed_time":0.6706037795,"remaining_time":0.1277340532},
{"learn":[0.08442942275],"iteration":168,"passed_time":0.6744038165,"remaining_time":0.1237072089},
{"learn":[0.08440685075],"iteration":169,"passed_time":0.6781964805,"remaining_time":0.1196817319},
{"learn":[0.08436557747],"iteration":170,"passed_time":0.6820068723,"remaining_time":0.1156619842},
{"learn":[0.08433954008],"iteration":171,"passed_time":0.6857448299,"remaining_time":0.1116328793},
{"learn":[0.0843136874],"iteration":172,"passed_time":0.6895420885,"remaining_time":0.1076163953},
{"learn":[0.08429863949],"iteration":173,"passed_time":0.693225557,"remaining_time":0.1035854281},
{"learn":[0.08427998551],"iteration":174,"passed_time":0.6969914897,"remaining_time":0.09957021281},
{"learn":[0.08425081533],"iteration":175,"passed_time":0.7007739617,"remaining_time":0.09556008569},
{"learn":[0.08422532534],"iteration":176,"passed_time":0.7043882515,"remaining_time":0.09153067675},
{"learn":[0.08417204557],"iteration":177,"passed_time":0.7081630781,"remaining_time":0.0875257737},
{"learn":[0.08415008449],"iteration":178,"passed_time":0.7119314716,"remaining_time":0.08352268662},
{"learn":[0.08408926436],"iteration":179,"passed_time":0.7155845572,"remaining_time":0.07950939524},
{"learn":[0.08404389934],"iteration":180,"passed_time":0.7194063782,"remaining_time":0.07551779661},
{"learn":[0.08403045107],"iteration":181,"passed_time":0.7230724029,"remaining_time":0.07151265523},
{"learn":[0.08398134537],"iteration":182,"passed_time":0.7267976074,"remaining_time":0.06751671763},
{"learn":[0.08396261283],"iteration":183,"passed_time":0.7306003249,"remaining_time":0.06353046303},
{"learn":[0.08394594115],"iteration":184,"passed_time":0.7344341774,"remaining_time":0.05954871708},
{"learn":[0.08391371355],"iteration":185,"passed_time":0.7381159788,"remaining_time":0.05555711669},
{"learn":[0.08387689626],"iteration":186,"passed_time":0.7419046955,"remaining_time":0.05157626226},
{"learn":[0.08386364325],"iteration":187,"passed_time":0.7457368714,"remaining_time":0.04760022583},
{"learn":[0.08383788613],"iteration":188,"passed_time":0.7515763834,"remaining_time":0.04374254083},
{"learn":[0.08379185974],"iteration":189,"passed_time":0.7567190957,"remaining_time":0.03982732082},
{"learn":[0.08377181982],"iteration":190,"passed_time":0.7700528881,"remaining_time":0.03628521462},
{"learn":[0.08372134518],"iteration":191,"passed_time":0.7794214009,"remaining_time":0.0324758917},
{"learn":[0.08370023262],"iteration":192,"passed_time":0.7849909144,"remaining_time":0.02847117306},
{"learn":[0.08364043334],"iteration":193,"passed_time":0.7930478644,"remaining_time":0.02452725354},
{"learn":[0.08361730823],"iteration":194,"passed_time":0.8031141392,"remaining_time":0.02059267024},
{"learn":[0.08359902872],"iteration":195,"passed_time":0.8162054262,"remaining_time":0.0166572536},
{"learn":[0.08357180857],"iteration":196,"passed_time":0.8259253057,"remaining_time":0.01257754273},
{"learn":[0.08355034214],"iteration":197,"passed_time":0.8375321931,"remaining_time":0.008459921143},
{"learn":[0.08353472305],"iteration":198,"passed_time":0.8465163744,"remaining_time":0.004253851128},
{"learn":[0.08350496006],"iteration":199,"passed_time":0.857357362,"remaining_time":0}
]}